kaftar/__init__.py
kaftar/main.py
kaftar/schemas.py
kaftar-0.2.2.dist-info/METADATA
kaftar-0.2.2.dist-info/WHEEL
kaftar-0.2.2.dist-info/top_level.txt
kaftar-0.2.2.dist-info/RECORD
