Metadata-Version: 2.1
Name: kaftar
Version: 0.2.2
Summary: a simple sdk to send notifications on queue for celery tasks
Author-email: Amirreza Taherkhani <amirrezataherkhaani@gmail.com>
Project-URL: Homepage, https://github.com/pypa/sampleproject
Classifier: Programming Language :: Python :: 3
Classifier: Operating System :: POSIX :: Linux
Requires-Python: >=3.8
Requires-Dist: celery ==5.3.1
